multimodalsim/__init__.py
multimodalsim/__main__.py
multimodalsim/config/config.py
multimodalsim/config/coordinates_osrm_config.py
multimodalsim/config/data_analyzer_config.py
multimodalsim/config/data_collector_config.py
multimodalsim/config/data_reader_config.py
multimodalsim/config/gtfs_generator_config.py
multimodalsim/config/optimization_config.py
multimodalsim/config/request_generator_config.py
multimodalsim/config/simulation_config.py
multimodalsim/config/ini/README.md
multimodalsim/config/ini/cap_requests_generator.ini
multimodalsim/config/ini/coordinates_osrm.ini
multimodalsim/config/ini/data_analyzer.ini
multimodalsim/config/ini/data_collector.ini
multimodalsim/config/ini/gtfs_data_reader.ini
multimodalsim/config/ini/gtfs_generator.ini
multimodalsim/config/ini/optimization.ini
multimodalsim/config/ini/simulation.ini
multimodalsim/coordinates/__init__.py
multimodalsim/coordinates/coordinates.py
multimodalsim/coordinates/coordinates_from_file.py
multimodalsim/coordinates/coordinates_from_polyline_file.py
multimodalsim/coordinates/coordinates_osrm.py
multimodalsim/logger/__init__.py
multimodalsim/logger/formatter.py
multimodalsim/observer/__init__.py
multimodalsim/observer/data_collector.py
multimodalsim/observer/environment_observer.py
multimodalsim/observer/visualizer.py
multimodalsim/optimization/__init__.py
multimodalsim/optimization/dispatcher.py
multimodalsim/optimization/optimization.py
multimodalsim/optimization/splitter.py
multimodalsim/optimization/state.py
multimodalsim/optimization/fixed_line/__init__.py
multimodalsim/optimization/fixed_line/fixed_line_dispatcher.py
multimodalsim/optimization/shuttle/__init__.py
multimodalsim/optimization/shuttle/shuttle_greedy_dispatcher.py
multimodalsim/optimization/shuttle/shuttle_hub_simple_dispatcher.py
multimodalsim/optimization/shuttle/shuttle_hub_simple_network_dispatcher.py
multimodalsim/reader/__init__.py
multimodalsim/reader/available_connections_extractor.py
multimodalsim/reader/data_reader.py
multimodalsim-0.0.1.dist-info/licenses/LICENSE
multimodalsim-0.0.1.dist-info/METADATA
multimodalsim-0.0.1.dist-info/WHEEL
multimodalsim-0.0.1.dist-info/top_level.txt
multimodalsim-0.0.1.dist-info/RECORD
