Metadata-Version: 2.4
Name: multimodalsim
Version: 0.0.1
Summary: A package to perform discrete-event simulations of a transportation system.
Home-page: 
Author: Laboratory for Combinatorial Optimization in Real-time Environment
Author-email: 
License-Expression: MIT
Project-URL: Homepage, https://github.com/lab-core/multimodal-simulator
Classifier: Programming Language :: Python :: 3
Classifier: Operating System :: OS Independent
Requires-Python: >=3.9
License-File: LICENSE
Requires-Dist: pip
Requires-Dist: networkx
Requires-Dist: numpy>=2.2.6
Requires-Dist: pandas>=2.2.3
Requires-Dist: requests
Requires-Dist: polyline
Requires-Dist: pyproj
Requires-Dist: matplotlib
Dynamic: license-file
